carla/__init__.py
carla/_version.py
carla/data_catalog.yaml
carla/logging.yaml
carla/mlmodel_catalog.yaml
carla/data/__init__.py
carla/data/api/__init__.py
carla/data/api/data.py
carla/data/catalog/__init__.py
carla/data/catalog/catalog.py
carla/data/catalog/csv_catalog.py
carla/data/catalog/load_data.py
carla/data/catalog/online_catalog.py
carla/data/causal_model/__init__.py
carla/data/causal_model/causal_model.py
carla/data/causal_model/synthethic_data.py
carla/data/load_catalog/__init__.py
carla/data/load_catalog/load_catalog.py
carla/data/load_scm/__init__.py
carla/data/load_scm/distributions.py
carla/data/load_scm/load_scm.py
carla/data/load_scm/scm.py
carla/data/pipelining/__init__.py
carla/data/pipelining/steps.py
carla/data/pipelining/transformers.py
carla/evaluation/__init__.py
carla/evaluation/benchmark.py
carla/evaluation/distances.py
carla/evaluation/nearest_neighbours.py
carla/evaluation/process_nans.py
carla/evaluation/redundancy.py
carla/evaluation/success_rate.py
carla/evaluation/violations.py
carla/models/__init__.py
carla/models/api/__init__.py
carla/models/api/mlmodel.py
carla/models/catalog/__init__.py
carla/models/catalog/catalog.py
carla/models/catalog/load_model.py
carla/models/catalog/parse_xgboost.py
carla/models/catalog/train_model.py
carla/models/catalog/trees.py
carla/models/catalog/ANN_TF/__init__.py
carla/models/catalog/ANN_TF/model_ann.py
carla/models/catalog/ANN_TORCH/__init__.py
carla/models/catalog/ANN_TORCH/model_ann.py
carla/models/catalog/Linear_TF/__init__.py
carla/models/catalog/Linear_TF/model_linear.py
carla/models/catalog/Linear_TORCH/__init__.py
carla/models/catalog/Linear_TORCH/model_linear.py
carla/models/negative_instances/__init__.py
carla/models/negative_instances/predict.py
carla/plotting/__init__.py
carla/plotting/barplot.py
carla/plotting/plotting.py
carla/plotting/stripplot.py
carla/plotting/swarmplot.py
carla/recourse_methods/__init__.py
carla/recourse_methods/api/__init__.py
carla_recourse-0.0.5.dist-info/METADATA
carla_recourse-0.0.5.dist-info/WHEEL
carla_recourse-0.0.5.dist-info/top_level.txt
carla_recourse-0.0.5.dist-info/RECORD
