Metadata-Version: 2.1
Name: carla-recourse
Version: 0.0.5
Summary: A library for counterfactual recourse
Home-page: https://github.com/carla-recourse/CARLA
Author: Martin Pawelczyk, Sascha Bielawski, Johannes van den Heuvel, Tobias Richter and Gjergji Kasneci
Author-email: martin.pawelczyk@uni-tuebingen.de
License: MIT
Classifier: License :: OSI Approved :: MIT License
Classifier: Programming Language :: Python :: 3
Classifier: Programming Language :: Python :: 3.7
Requires-Dist: lime (==0.2.0.1)
Requires-Dist: mip (==1.12.0)
Requires-Dist: numpy (==1.19.4)
Requires-Dist: pandas (==1.1.4)
Requires-Dist: recourse (==1.0.0)
Requires-Dist: scikit-learn (==0.23.2)
Requires-Dist: tensorflow (==1.14.0)
Requires-Dist: torch (==1.7.0)
Requires-Dist: torchvision (==0.8.1)
Requires-Dist: h5py (==2.10.0)
Requires-Dist: dice-ml (==0.5)
Requires-Dist: ipython
Requires-Dist: keras (==2.3.0)
Requires-Dist: xgboost (==1.4.2)
Requires-Dist: causalgraphicalmodels (==0.0.4)
